time_in/__init__.py
time_in/__main__.py
time_in/countryinfo.py
time_in/py.typed
time_in-0.1.1.dist-info/LICENSE
time_in-0.1.1.dist-info/METADATA
time_in-0.1.1.dist-info/WHEEL
time_in-0.1.1.dist-info/entry_points.txt
time_in-0.1.1.dist-info/top_level.txt
time_in-0.1.1.dist-info/RECORD
