Metadata-Version: 2.1
Name: time-in
Version: 0.1.1
Summary: CLI tool to figure out the time somewhere else
Home-page: https://github.com/seanbreckenridge/time-in
Author: Sean Breckenridge
Author-email: seanbrecke@gmail.com
License: MIT
Classifier: License :: OSI Approved :: MIT License
Classifier: Programming Language :: Python
Classifier: Programming Language :: Python :: 3
Classifier: Programming Language :: Python :: 3.8
Classifier: Programming Language :: Python :: 3.9
Classifier: Programming Language :: Python :: 3.10
Classifier: Programming Language :: Python :: 3.11
Requires-Python: >=3.9
License-File: LICENSE
Requires-Dist: click (>=8.1.6)
Requires-Dist: tzdata
Requires-Dist: tabulate
Requires-Dist: pyfzf-iter
Requires-Dist: tzlocal (>=5.0)
Requires-Dist: dateparser
Provides-Extra: testing
Requires-Dist: mypy ; extra == 'testing'
Requires-Dist: flake8 ; extra == 'testing'
